.gitignore
.pylintrc
LICENSE
MANIFEST.in
Makefile
README.md
dev-requirements.txt
requirements.txt
setup.py
docs/conf.py
docs/index.rst
docs/source/completion.rst
docs/source/intro.rst
docs/source/quick-start.rst
images/logo.png
macrame/__init__.py
macrame/__main__.py
macrame/app.py
macrame/makefile.py
macrame/test.py
macrame.egg-info/PKG-INFO
macrame.egg-info/SOURCES.txt
macrame.egg-info/dependency_links.txt
macrame.egg-info/entry_points.txt
macrame.egg-info/requires.txt
macrame.egg-info/top_level.txt
macrame/command/buildCommand.py
macrame/command/cleanCommand.py
macrame/command/infoCommand.py
macrame/command/parser.py
macrame/command/runCommand.py
macrame/command/todoCommand.py
macrame/command/toolCommand.py
macrame/configuration/config.py
macrame/core/cli.py
macrame/core/complete.py
macrame/core/completion.bash
macrame/core/completion.zsh
macrame/core/exceptions.py
macrame/core/utils.py
macrame/core/version.py
static/Makefile
static/compiler.mk
static/tests.mk
static/scripts/get_fw_size
static/scripts/get_version.sh
static/scripts/pclint_settings
tests/test_macrame_core_version.py