Metadata-Version: 2.1
Name: macrame
Version: 0.0.1
Summary: Utility to build Assembly/C/C++ projects
Home-page: https://github.com/TediCreations/macrame
Author: Kanelis Elias
Author-email: hkanelhs@yahoo.gr
License: MIT
Download-URL: https://github.com/TediCreations/macrame/archive/Unknown.tar.gz
Keywords: build,make,util
Platform: UNKNOWN
Classifier: Development Status :: 3 - Alpha
Classifier: Intended Audience :: Developers
Classifier: Topic :: Software Development :: Build Tools
Classifier: License :: OSI Approved :: MIT License
Classifier: Programming Language :: Python :: 3
Classifier: Programming Language :: Python :: 3.6
License-File: LICENSE
